src/__init__.py
src/client.py
src/config.json
src/grobid_client.py
src/main.py
artitle-0.0.1.dist-info/LICENSE
artitle-0.0.1.dist-info/METADATA
artitle-0.0.1.dist-info/WHEEL
artitle-0.0.1.dist-info/entry_points.txt
artitle-0.0.1.dist-info/top_level.txt
artitle-0.0.1.dist-info/RECORD
