Metadata-Version: 2.1
Name: artitle
Version: 0.0.1
License-File: LICENSE
Requires-Dist: requests
Requires-Dist: argparse
